treekit/.DS_Store
treekit/__about__.py
treekit/__init__.py
treekit/__pycache__/__about__.cpython-38.pyc
treekit/__pycache__/__init__.cpython-38.pyc
treekit/binarytree/__init__.py
treekit/binarytree/_binarytree.py
treekit/binarytree/__pycache__/__init__.cpython-38.pyc
treekit/binarytree/__pycache__/__init__.cpython-39.pyc
treekit/binarytree/__pycache__/_binarytree.cpython-38.pyc
treekit/binarytree/__pycache__/_binarytree.cpython-39.pyc
treekit/examples/BST_height=4.png
treekit/examples/Fibonacci_Numbers_Generalized_n=15_order=8.png
treekit/examples/Fibonacci_Numbers_n=5.png
treekit/examples/Fibonacci_Numbers_n=5.pptx
treekit/examples/MaxHeap1.png
treekit/examples/Remove_Invalid_Parentheses.png
treekit/examples/Word_Break_DFS_Search_Space.png
treekit/heap/__init__.py
treekit/heap/_heap.py
treekit/heap/__pycache__/__init__.cpython-38.pyc
treekit/heap/__pycache__/_heap.cpython-38.pyc
treekit/tree/__init__.py
treekit/tree/_tree.py
treekit/tree/__pycache__/__init__.cpython-38.pyc
treekit/tree/__pycache__/__init__.cpython-39.pyc
treekit/tree/__pycache__/_tree.cpython-38.pyc
treekit/tree/__pycache__/_tree.cpython-39.pyc
treekit/tree/images/inorder_recursion.png
treekit-0.0.22.dist-info/LICENSE
treekit-0.0.22.dist-info/METADATA
treekit-0.0.22.dist-info/WHEEL
treekit-0.0.22.dist-info/top_level.txt
treekit-0.0.22.dist-info/RECORD
