Metadata-Version: 2.1
Name: treekit
Version: 0.0.22
Summary: Library for Studying and Applying Tree Data Structure
Home-page: https://github.com/daniel-yj-yang/treekit
Author: Daniel Yang
Author-email: daniel.yj.yang@gmail.com
License: MIT
Platform: UNKNOWN
Classifier: Development Status :: 3 - Alpha
Classifier: Programming Language :: Python :: 3
Classifier: Programming Language :: Python :: 3.8
Classifier: Programming Language :: Python :: 3.9
Classifier: License :: OSI Approved :: MIT License
Classifier: Operating System :: OS Independent
Requires-Python: >=3.8
License-File: LICENSE
Requires-Dist: pyvis (>=0.1.9)
